{"id":"4900","user":{"id":"136399","nickname":"可执行程序.exe","avatar_url":"https://static.codemao.cn/FoEkoH9i9BIHIRbNiseYD7nhDCUh?attname=","subject_id":0,"work_shop_name":"","work_shop_level":0,"wuhan_medal":false,"has_signed":false},"title":"这么好的东西怎么没人呢？","content":"<p><a rel=\"nofollow\"></a><a href=\"https://idestable.codemao.cn/work/iframe/34125?control_bar=true?hide_praise=true\" rel=\"nofollow\">https://idestable.codemao.cn/work/iframe/34125?control_bar=true?hide_praise=true</a></p>\n<p><br></p>","board_id":"7","board_name":"灌水池塘","updated_at":1500098934,"created_at":1500087137,"n_views":102,"n_replies":6,"n_comments":0,"is_authorized":false,"is_featured":false,"is_hotted":false,"is_pinned":false,"tutorial_flag":0,"ask_help_flag":0}