{"id":"5763","user":{"id":"267611","nickname":"好动的训练师267611","avatar_url":"https://static-user-center.codemao.cn/user_0000.png","subject_id":0,"work_shop_name":"","work_shop_level":0,"wuhan_medal":false,"has_signed":false},"title":"黑河是什么","content":"<p>黑河是什么</p>","board_id":"7","board_name":"灌水池塘","updated_at":1503319199,"created_at":1503317727,"n_views":42,"n_replies":11,"n_comments":0,"is_authorized":false,"is_featured":false,"is_hotted":false,"is_pinned":false,"tutorial_flag":0,"ask_help_flag":0}