{"items":[{"id":"1273736","user":{"id":"5647629","nickname":"是HYS星雲ah","avatar_url":"https://cdn-community.codemao.cn/47/community/d2ViXzEwMDFfNTY0NzYyOV81NjQ3NjI5XzE2NTQ0MjI4NDM1ODJfYTk4YTYzY2Q.jpeg","subject_id":2617,"work_shop_name":"幻影工作室（极地区域）","work_shop_level":2,"wuhan_medal":false,"has_signed":false},"is_top":false,"n_likes":0,"is_liked":false,"content":"<p>烤骨</p>","n_comments":0,"updated_at":1653280343,"created_at":1653280343,"earliest_comments":[]},{"id":"724711","user":{"id":"2876144","nickname":"我是谁..","avatar_url":"https://cdn-community.codemao.cn/47/community/1595304224912t01dc4cc5245378bd72.gif","subject_id":818,"work_shop_name":"唯爱工作室｜三周年","work_shop_level":3,"wuhan_medal":false,"has_signed":false},"is_top":false,"n_likes":0,"is_liked":false,"content":"<p>挖&nbsp;</p>","n_comments":0,"updated_at":1596619899,"created_at":1596619899,"earliest_comments":[]},{"id":"105545","user":{"id":"502960","nickname":"嗯哼君 渠源","avatar_url":"https://cdn-community.codemao.cn/47/community/d2ViXzEwMDFfNTAyOTYwXzUwMjk2MF8xNjIzODUzNjUwMDU0X2JmZjU0MzY4.jpeg","subject_id":0,"work_shop_name":"","work_shop_level":0,"wuhan_medal":false,"has_signed":false},"is_top":false,"n_likes":0,"is_liked":false,"content":"<p><p>挖坟</p> \n<p>&nbsp;</p></p>","n_comments":1,"updated_at":1535521612,"created_at":1535521612,"earliest_comments":[{"id":"853331","user":{"id":"4316780","nickname":"某雀罒ω罒（认准正版雀）◐_◑｡◕‿◕｡","avatar_url":"https://cdn-community.codemao.cn/47/community/1596100006138旋转的呆萌小太阳.gif","subject_id":823,"work_shop_name":"学生党工作室","work_shop_level":1,"wuhan_medal":false,"has_signed":false},"n_likes":0,"is_liked":false,"content":"挖····","created_at":1596620650}]},{"id":"8402","user":{"id":"202339","nickname":"赵翊丞男一号","avatar_url":"https://online-education.codemao.cn//229/codemaokids/88c1687534a04be3b3221665a798d64b.png","subject_id":0,"work_shop_name":"","work_shop_level":0,"wuhan_medal":false,"has_signed":false},"is_top":false,"n_likes":0,"is_liked":false,"content":"<p>啊噢。。。。<img src=\"http://img.t.sinajs.cn/t4/appstyle/expression/ext/normal/f4/cj_thumb.gif\">好像不太对劲</p>\n<p><br></p>","n_comments":0,"updated_at":1484198011,"created_at":1484198011,"earliest_comments":[]},{"id":"8396","user":{"id":"198051","nickname":"玄天天天天","avatar_url":"https://static.codemao.cn/FubivxgZ6g9xtAXVZ6h8oeFw-mPA","subject_id":0,"work_shop_name":"","work_shop_level":0,"wuhan_medal":false,"has_signed":false},"is_top":false,"n_likes":0,"is_liked":false,"content":"<p>喵</p>\n<p><br></p>","n_comments":0,"updated_at":1484188973,"created_at":1484188973,"earliest_comments":[]},{"id":"8380","user":{"id":"102083","nickname":"柠檬不酸","avatar_url":"https://static.codemao.cn/Fig9ZkHvtnb2N1t4i8eiOHP502Pk?attname=","subject_id":0,"work_shop_name":"","work_shop_level":0,"wuhan_medal":false,"has_signed":false},"is_top":false,"n_likes":0,"is_liked":false,"content":"<p>这是在比钱吗<img src=\"http://img.t.sinajs.cn/t4/appstyle/expression/ext/normal/91/h_thumb.gif\"></p>\n<p><br></p>","n_comments":0,"updated_at":1484111307,"created_at":1484111307,"earliest_comments":[]},{"id":"8379","user":{"id":"180879","nickname":"这个名字没人用","avatar_url":"https://static-user-center.codemao.cn/user_0003.png","subject_id":0,"work_shop_name":"","work_shop_level":0,"wuhan_medal":false,"has_signed":false},"is_top":false,"n_likes":0,"is_liked":false,"content":"<p>我3941金币</p>","n_comments":0,"updated_at":1484106879,"created_at":1484106879,"earliest_comments":[]},{"id":"8269","user":{"id":"197888","nickname":"能天使","avatar_url":"https://static.codemao.cn/FpCgZyR7DDcd8AHUffttmtdDM2Ad?attname=","subject_id":0,"work_shop_name":"","work_shop_level":0,"wuhan_medal":false,"has_signed":false},"is_top":false,"n_likes":0,"is_liked":false,"content":"<p>我说，钱是用来攀比的吗？</p>\n<p><br></p>","n_comments":0,"updated_at":1483710857,"created_at":1483710857,"earliest_comments":[]},{"id":"8195","user":{"id":"194148","nickname":"MAlopos","avatar_url":"https://cdn-community.codemao.cn/47/community/d2ViXzEwMDFfMTk0MTQ4XzE5NDE0OF8xNjEzMzExNDQ1ODY5XzZlYmRkN2E0.jpeg","subject_id":615,"work_shop_name":"萌新院","work_shop_level":2,"wuhan_medal":false,"has_signed":false},"is_top":false,"n_likes":0,"is_liked":false,"content":"<p>@<a rel=\"nofollow\">冰花柔雪~唯美梦樱</a>你都不做任务还想要金币<br></p>","n_comments":0,"updated_at":1483537785,"created_at":1483537785,"earliest_comments":[]},{"id":"7921","user":{"id":"200685","nickname":"夏若曦-柔柔","avatar_url":"https://static.codemao.cn/FpfIBeYQjIcuWOTDDaUg_sEA4t5v?attname=","subject_id":0,"work_shop_name":"","work_shop_level":0,"wuhan_medal":false,"has_signed":false},"is_top":false,"n_likes":0,"is_liked":false,"content":"<p><img src=\"http://img.t.sinajs.cn/t4/appstyle/expression/ext/normal/90/money_thumb.gif\"><img src=\"http://img.t.sinajs.cn/t4/appstyle/expression/ext/normal/90/money_thumb.gif\"><img src=\"http://img.t.sinajs.cn/t4/appstyle/expression/ext/normal/90/money_thumb.gif\"><br></p>\n<p><br></p>","n_comments":0,"updated_at":1482652386,"created_at":1482652386,"earliest_comments":[]},{"id":"7882","user":{"id":"194148","nickname":"MAlopos","avatar_url":"https://cdn-community.codemao.cn/47/community/d2ViXzEwMDFfMTk0MTQ4XzE5NDE0OF8xNjEzMzExNDQ1ODY5XzZlYmRkN2E0.jpeg","subject_id":615,"work_shop_name":"萌新院","work_shop_level":2,"wuhan_medal":false,"has_signed":false},"is_top":false,"n_likes":0,"is_liked":false,"content":"<p>增加到5000</p>","n_comments":0,"updated_at":1482502363,"created_at":1482502363,"earliest_comments":[]},{"id":"7881","user":{"id":"194148","nickname":"MAlopos","avatar_url":"https://cdn-community.codemao.cn/47/community/d2ViXzEwMDFfMTk0MTQ4XzE5NDE0OF8xNjEzMzExNDQ1ODY5XzZlYmRkN2E0.jpeg","subject_id":615,"work_shop_name":"萌新院","work_shop_level":2,"wuhan_medal":false,"has_signed":false},"is_top":false,"n_likes":0,"is_liked":false,"content":"<p>才775！我比你多多了</p>","n_comments":0,"updated_at":1482502307,"created_at":1482502307,"earliest_comments":[]},{"id":"7879","user":{"id":"139365","nickname":"韵律源点Arcaea","avatar_url":"https://cdn-community.codemao.cn/47/community/d2ViXzEwMDFfMTM5MzY1XzEzOTM2NV8xNjU0MDAxNjQ0NTE5XzI3MGQwOTRh.png","subject_id":5482,"work_shop_name":"咕咕咕咕咕咕咕（）","work_shop_level":2,"wuhan_medal":false,"has_signed":false},"is_top":false,"n_likes":0,"is_liked":false,"content":"<p>你们是在抢钱吗？我都775了。哎呀，这样会不会被雷劈呢？<img src=\"https://static.codemao.cn/emoji/codemao/5.gif\"></p>\n<p><br></p>","n_comments":0,"updated_at":1482499924,"created_at":1482499924,"earliest_comments":[]},{"id":"7878","user":{"id":"139365","nickname":"韵律源点Arcaea","avatar_url":"https://cdn-community.codemao.cn/47/community/d2ViXzEwMDFfMTM5MzY1XzEzOTM2NV8xNjU0MDAxNjQ0NTE5XzI3MGQwOTRh.png","subject_id":5482,"work_shop_name":"咕咕咕咕咕咕咕（）","work_shop_level":2,"wuhan_medal":false,"has_signed":false},"is_top":false,"n_likes":0,"is_liked":false,"content":"<p><img src=\"http://img.t.sinajs.cn/t4/appstyle/expression/ext/normal/90/money_thumb.gif\"><img src=\"http://img.t.sinajs.cn/t4/appstyle/expression/ext/normal/90/money_thumb.gif\"><img src=\"http://img.t.sinajs.cn/t4/appstyle/expression/ext/normal/90/money_thumb.gif\"><img src=\"http://img.t.sinajs.cn/t4/appstyle/expression/ext/normal/90/money_thumb.gif\"><img src=\"http://img.t.sinajs.cn/t4/appstyle/expression/ext/normal/90/money_thumb.gif\"><br></p>\n<p><br></p>","n_comments":0,"updated_at":1482499830,"created_at":1482499830,"earliest_comments":[]},{"id":"7869","user":{"id":"102240","nickname":"飞翔的余","avatar_url":"https://static.codemao.cn/FkZkpSadYcnCph2GRQ5buKVdGqvo","subject_id":0,"work_shop_name":"","work_shop_level":0,"wuhan_medal":false,"has_signed":false},"is_top":false,"n_likes":0,"is_liked":false,"content":"<p>我13000多金币</p>","n_comments":0,"updated_at":1482493447,"created_at":1482493447,"earliest_comments":[]},{"id":"7759","user":{"id":"194148","nickname":"MAlopos","avatar_url":"https://cdn-community.codemao.cn/47/community/d2ViXzEwMDFfMTk0MTQ4XzE5NDE0OF8xNjEzMzExNDQ1ODY5XzZlYmRkN2E0.jpeg","subject_id":615,"work_shop_name":"萌新院","work_shop_level":2,"wuhan_medal":false,"has_signed":false},"is_top":false,"n_likes":0,"is_liked":false,"content":"<p><img src=\"http://img.t.sinajs.cn/t4/appstyle/expression/ext/normal/90/money_thumb.gif\"><br></p>\n<p><br></p>","n_comments":0,"updated_at":1481974465,"created_at":1481974465,"earliest_comments":[]},{"id":"7757","user":{"id":"101860","nickname":"四片叶de三叶吖","avatar_url":"https://static.codemao.cn/FqcR23gyTBxqpGDVypZpJe8hw4uq","subject_id":0,"work_shop_name":"","work_shop_level":0,"wuhan_medal":false,"has_signed":false},"is_top":false,"n_likes":0,"is_liked":false,"content":"<p>我10000多金币</p>","n_comments":0,"updated_at":1481974083,"created_at":1481974083,"earliest_comments":[]},{"id":"7756","user":{"id":"194148","nickname":"MAlopos","avatar_url":"https://cdn-community.codemao.cn/47/community/d2ViXzEwMDFfMTk0MTQ4XzE5NDE0OF8xNjEzMzExNDQ1ODY5XzZlYmRkN2E0.jpeg","subject_id":615,"work_shop_name":"萌新院","work_shop_level":2,"wuhan_medal":false,"has_signed":false},"is_top":false,"n_likes":0,"is_liked":false,"content":"<p>别人购买作品和上课就能赚这么多金币<img src=\"http://img.t.sinajs.cn/t4/appstyle/expression/ext/normal/6a/laugh.gif\"></p>\n<p><br></p>","n_comments":0,"updated_at":1481973254,"created_at":1481973254,"earliest_comments":[]},{"id":"7745","user":{"id":"179901","nickname":"sunshine","avatar_url":"https://static-user-center.codemao.cn/user_0009.png","subject_id":0,"work_shop_name":"","work_shop_level":0,"wuhan_medal":false,"has_signed":false},"is_top":false,"n_likes":0,"is_liked":false,"content":"<p>我10</p>","n_comments":0,"updated_at":1481954180,"created_at":1481954180,"earliest_comments":[]},{"id":"7737","user":{"id":"202990","nickname":"随她","avatar_url":"https://static-user-center.codemao.cn/user_0002.png","subject_id":0,"work_shop_name":"","work_shop_level":0,"wuhan_medal":false,"has_signed":false},"is_top":false,"n_likes":0,"is_liked":false,"content":"<p>你怎么赚的那么多金币！<img src=\"http://img.t.sinajs.cn/t4/appstyle/expression/ext/normal/af/cry.gif\"></p>\n<p><br></p>","n_comments":0,"updated_at":1481947659,"created_at":1481947659,"earliest_comments":[]},{"id":"7729","user":{"id":"194148","nickname":"MAlopos","avatar_url":"https://cdn-community.codemao.cn/47/community/d2ViXzEwMDFfMTk0MTQ4XzE5NDE0OF8xNjEzMzExNDQ1ODY5XzZlYmRkN2E0.jpeg","subject_id":615,"work_shop_name":"萌新院","work_shop_level":2,"wuhan_medal":false,"has_signed":false},"is_top":false,"n_likes":0,"is_liked":false,"content":"<p>增加到2000</p>","n_comments":0,"updated_at":1481939436,"created_at":1481939436,"earliest_comments":[]},{"id":"7728","user":{"id":"194148","nickname":"MAlopos","avatar_url":"https://cdn-community.codemao.cn/47/community/d2ViXzEwMDFfMTk0MTQ4XzE5NDE0OF8xNjEzMzExNDQ1ODY5XzZlYmRkN2E0.jpeg","subject_id":615,"work_shop_name":"萌新院","work_shop_level":2,"wuhan_medal":false,"has_signed":false},"is_top":false,"n_likes":0,"is_liked":false,"content":"<p>我现在都3134了</p>","n_comments":0,"updated_at":1481939421,"created_at":1481939421,"earliest_comments":[]},{"id":"7319","user":{"id":"194148","nickname":"MAlopos","avatar_url":"https://cdn-community.codemao.cn/47/community/d2ViXzEwMDFfMTk0MTQ4XzE5NDE0OF8xNjEzMzExNDQ1ODY5XzZlYmRkN2E0.jpeg","subject_id":615,"work_shop_name":"萌新院","work_shop_level":2,"wuhan_medal":false,"has_signed":false},"is_top":false,"n_likes":0,"is_liked":false,"content":"<p>还想要什么?</p>","n_comments":0,"updated_at":1479981972,"created_at":1479981972,"earliest_comments":[]},{"id":"7302","user":{"id":"202990","nickname":"随她","avatar_url":"https://static-user-center.codemao.cn/user_0002.png","subject_id":0,"work_shop_name":"","work_shop_level":0,"wuhan_medal":false,"has_signed":false},"is_top":false,"n_likes":0,"is_liked":false,"content":"<p>奖励可以多一点吗？</p>","n_comments":0,"updated_at":1479890036,"created_at":1479890036,"earliest_comments":[]},{"id":"7295","user":{"id":"194148","nickname":"MAlopos","avatar_url":"https://cdn-community.codemao.cn/47/community/d2ViXzEwMDFfMTk0MTQ4XzE5NDE0OF8xNjEzMzExNDQ1ODY5XzZlYmRkN2E0.jpeg","subject_id":615,"work_shop_name":"萌新院","work_shop_level":2,"wuhan_medal":false,"has_signed":false},"is_top":false,"n_likes":0,"is_liked":false,"content":"<p>@胡咚咚不要还不给现在是140金币</p>","n_comments":0,"updated_at":1479815644,"created_at":1479815644,"earliest_comments":[]},{"id":"7226","user":{"id":"196020","nickname":"阿短","avatar_url":"https://cdn-community.codemao.cn/47/community/d2ViXzEwMDFfMTk2MDIwXzE5NjAyMF8xNjE1NjQxNDI5MjExXzM4OGU2N2Zh.png","subject_id":0,"work_shop_name":"","work_shop_level":0,"wuhan_medal":false,"has_signed":false},"is_top":false,"n_likes":0,"is_liked":false,"content":"<p>给我，我现在只有1金币（才怪）</p>","n_comments":0,"updated_at":1479638428,"created_at":1479638428,"earliest_comments":[]},{"id":"7193","user":{"id":"101954","nickname":"胡咚咚","avatar_url":"https://static.codemao.cn/a015bcb7-f868-4895-a24c-2410e4d13147","subject_id":0,"work_shop_name":"","work_shop_level":0,"wuhan_medal":false,"has_signed":false},"is_top":false,"n_likes":0,"is_liked":false,"content":"<p>才40，谁干啊？切<img src=\"https://static.codemao.cn/emoji/codemao/5.gif\"></p>\n<p><br></p>","n_comments":0,"updated_at":1479560411,"created_at":1479560411,"earliest_comments":[]},{"id":"7173","user":{"id":"194148","nickname":"MAlopos","avatar_url":"https://cdn-community.codemao.cn/47/community/d2ViXzEwMDFfMTk0MTQ4XzE5NDE0OF8xNjEzMzExNDQ1ODY5XzZlYmRkN2E0.jpeg","subject_id":615,"work_shop_name":"萌新院","work_shop_level":2,"wuhan_medal":false,"has_signed":false},"is_top":false,"n_likes":0,"is_liked":false,"content":"<p>70</p>","n_comments":0,"updated_at":1479539692,"created_at":1479539692,"earliest_comments":[]},{"id":"6911","user":{"id":"194148","nickname":"MAlopos","avatar_url":"https://cdn-community.codemao.cn/47/community/d2ViXzEwMDFfMTk0MTQ4XzE5NDE0OF8xNjEzMzExNDQ1ODY5XzZlYmRkN2E0.jpeg","subject_id":615,"work_shop_name":"萌新院","work_shop_level":2,"wuhan_medal":false,"has_signed":false},"is_top":false,"n_likes":0,"is_liked":false,"content":"<p><span style=\"line-height: 1.8;\">嗯。。我给你们一个任务，谁先完成，就奖励谁40金币，剩余我自己留着啦</span><img src=\"http://img.t.sinajs.cn/t4/appstyle/expression/ext/normal/e9/sk_thumb.gif\"><br></p>\n<p>任务：所有素材都用版面绘制，做一个编程猫历险记的故事。</p>","n_comments":0,"updated_at":1478436805,"created_at":1478436805,"earliest_comments":[]},{"id":"6908","user":{"id":"101954","nickname":"胡咚咚","avatar_url":"https://static.codemao.cn/a015bcb7-f868-4895-a24c-2410e4d13147","subject_id":0,"work_shop_name":"","work_shop_level":0,"wuhan_medal":false,"has_signed":false},"is_top":false,"n_likes":0,"is_liked":false,"content":"<p>你送天驰金币？他是编程猫的创始人兼CEO，他送你还差不多，要不送我吧！<img src=\"http://img.t.sinajs.cn/t4/appstyle/expression/ext/normal/20/huanglianse_thumb.gif\"></p>\n<p><br></p>","n_comments":0,"updated_at":1478433399,"created_at":1478433399,"earliest_comments":[]}],"offset":0,"limit":30,"total":37,"counted":true}