{"id":"5312","user":{"id":"194148","nickname":"MAlopos","avatar_url":"https://cdn-community.codemao.cn/47/community/d2ViXzEwMDFfMTk0MTQ4XzE5NDE0OF8xNjEzMzExNDQ1ODY5XzZlYmRkN2E0.jpeg","subject_id":615,"work_shop_name":"萌新院","work_shop_level":2,"wuhan_medal":false,"has_signed":false},"title":"【前情】bug再现","content":"<p><img src=\"https://static.codemao.cn/FtxV22PO2ymwTROFcVvrAQxPOeqv\"><img src=\"https://static.codemao.cn/Fp4gw7Nf6OOF6cx_BKWhdEjWHiTl\"><br></p>\n<p><img src=\"https://static.codemao.cn/FtC_w5GfNfuQqgOJmTb99chpnhZi\"><img src=\"https://static.codemao.cn/FhjEisax45DgHPrR2fBXYKrBZxzE\"><br></p>\n<p><img src=\"https://static.codemao.cn/FrsipRgo7x1jkxIui27yJLm4QjBP\"><img src=\"https://static.codemao.cn/FiHAwus093cA1x4KlPbJezbCFOo1\"><br></p>\n<p><img src=\"https://static.codemao.cn/FjnXfFx9ITAL1Mgz1M26AE0dvIaM\"><br></p>\n<p>emmm......我弄不了视频啊</p>\n<p>怎么办，怎么办！</p>\n<p>只能截图</p>\n<p>求编程猫授权！<img src=\"https://static.codemao.cn/FhVGnZbdrvD8ipaxTD283o0QdOOa\"></p>\n<p>（借图）</p>","board_id":"5","board_name":"你问我答","updated_at":1501987855,"created_at":1501764569,"n_views":221,"n_replies":24,"n_comments":0,"is_authorized":false,"is_featured":false,"is_hotted":false,"is_pinned":false,"tutorial_flag":0,"ask_help_flag":0}