{"items":[{"id":"245383","user":{"id":"139365","nickname":"韵律源点Arcaea","avatar_url":"https://cdn-community.codemao.cn/47/community/d2ViXzEwMDFfMTM5MzY1XzEzOTM2NV8xNjU0MDAxNjQ0NTE5XzI3MGQwOTRh.png","subject_id":5482,"work_shop_name":"咕咕咕咕咕咕咕（）","work_shop_level":2,"wuhan_medal":false,"has_signed":false},"is_top":false,"n_likes":0,"is_liked":false,"content":"<p>洛阳铲</p>","n_comments":0,"updated_at":1581826317,"created_at":1581826317,"earliest_comments":[]},{"id":"124678","user":{"id":"1134087","nickname":"小企鹅飞","avatar_url":"https://static-platform.codemao.cn/production/avatar/custom/fad83d76-742f-47f2-b0a2-9b005950b928","subject_id":6415,"work_shop_name":"企鹅工作室","work_shop_level":1,"wuhan_medal":false,"has_signed":false},"is_top":false,"n_likes":0,"is_liked":false,"content":"<p>哈哈</p>","n_comments":0,"updated_at":1544243463,"created_at":1544243463,"earliest_comments":[]},{"id":"124561","user":{"id":"471278","nickname":"秋葵","avatar_url":"https://static.codemao.cn/FqOpovCnR74JGdrKD4Ut8UprxIUD","subject_id":615,"work_shop_name":"萌新院","work_shop_level":2,"wuhan_medal":false,"has_signed":false},"is_top":false,"n_likes":0,"is_liked":false,"content":"<p><p>在这里种下小小的愿望</p> \n<p>希望通天塔越来越好</p> \n<p>希望编程猫越来越好！</p></p>","n_comments":0,"updated_at":1544192761,"created_at":1544192761,"earliest_comments":[]},{"id":"87006","user":{"id":"337130","nickname":"绝命徒神探","avatar_url":"https://static.codemao.cn/FpCHOmz10RBEcUMzkZhHX-o75Upr","subject_id":0,"work_shop_name":"","work_shop_level":0,"wuhan_medal":false,"has_signed":false},"is_top":false,"n_likes":0,"is_liked":false,"content":"<p>摸金校尉</p>","n_comments":0,"updated_at":1530579648,"created_at":1530579648,"earliest_comments":[]},{"id":"86879","user":{"id":"145690","nickname":"苏某","avatar_url":"https://static.codemao.cn/FqfZiNb9syfl1XOK5rA7h-n3J7XY","subject_id":928,"work_shop_name":"波特工作室","work_shop_level":1,"wuhan_medal":false,"has_signed":false},"is_top":false,"n_likes":0,"is_liked":false,"content":"<p><img src=\"https://static.codemao.cn/Fg6Ra1e87QErHYFXAk90Er6o9ti4\"><br></p>\n<p><img src=\"https://static.codemao.cn/FuB4b8x92Sf4rBRoVshs8vJ458xz\"><br></p>\n<p><br></p>","n_comments":0,"updated_at":1530523451,"created_at":1530523451,"earliest_comments":[]},{"id":"36698","user":{"id":"194533","nickname":"成成4","avatar_url":"https://static-platform.codemao.cn/production/avatar/custom/98c02e00-76a4-4718-a87b-66f870e81387","subject_id":0,"work_shop_name":"","work_shop_level":0,"wuhan_medal":false,"has_signed":false},"is_top":false,"n_likes":0,"is_liked":false,"content":"<p><img src=\"https://static.codemao.cn/Fk2tPaCgW_9v7qZbD-TKGKw7g1jr\"><br></p>\n<p>什么意思啊啊啊啊啊啊啊啊啊啊啊啊啊啊啊啊啊啊啊啊啊啊啊啊啊啊啊啊啊啊啊啊啊啊啊啊啊啊啊啊啊啊啊啊啊啊啊啊啊啊啊啊啊啊啊啊啊啊啊啊啊啊啊啊啊啊啊啊啊啊啊啊啊啊啊啊啊啊啊啊啊啊啊啊啊啊啊啊啊啊啊啊啊啊啊啊啊啊啊啊啊啊啊啊啊啊啊啊啊啊啊啊啊啊啊啊啊啊啊啊啊啊啊啊啊啊啊啊？？？？？？？？？？？？？？？？？？？？？？？？？？？？？？？？？？？？？？？？？？？？？？？？？？？？？？？？？？？？？？？？？？？？？？？？？？？？？？？？？？？？？？？？？？？？？？？？？？？？？？</p>\n<p><br></p>","n_comments":1,"updated_at":1503300354,"created_at":1503300354,"earliest_comments":[{"id":"4443","user":{"id":"145690","nickname":"苏某","avatar_url":"https://static.codemao.cn/FqfZiNb9syfl1XOK5rA7h-n3J7XY","subject_id":928,"work_shop_name":"波特工作室","work_shop_level":1,"wuhan_medal":false,"has_signed":false},"n_likes":0,"is_liked":false,"content":"6666","created_at":1530242387}]},{"id":"36555","user":{"id":"203577","nickname":"技术喵","avatar_url":"https://static.codemao.cn/FjdGLKY8l4RINPdZ02073fwKFxPK","subject_id":228,"work_shop_name":"编程猫官方","work_shop_level":4,"wuhan_medal":false,"has_signed":false},"is_top":false,"n_likes":0,"is_liked":false,"content":"<p><img src=\"https://static.codemao.cn/FkoLSGOn7HnomigpolQyas0lwXhU\"><br></p>\n<p><img src=\"https://static.codemao.cn/emoji/codemao/2.gif\"><img src=\"https://static.codemao.cn/emoji/codemao/2.gif\"><img src=\"https://static.codemao.cn/emoji/codemao/2.gif\"><br></p>\n<p><br></p>","n_comments":1,"updated_at":1503224722,"created_at":1503224722,"earliest_comments":[{"id":"4874","user":{"id":"337130","nickname":"绝命徒神探","avatar_url":"https://static.codemao.cn/FpCHOmz10RBEcUMzkZhHX-o75Upr","subject_id":0,"work_shop_name":"","work_shop_level":0,"wuhan_medal":false,"has_signed":false},"n_likes":0,"is_liked":false,"content":"有哇在运用有对象这一说的编程语言里……","created_at":1530579615}]},{"id":"36522","user":{"id":"139365","nickname":"韵律源点Arcaea","avatar_url":"https://cdn-community.codemao.cn/47/community/d2ViXzEwMDFfMTM5MzY1XzEzOTM2NV8xNjU0MDAxNjQ0NTE5XzI3MGQwOTRh.png","subject_id":5482,"work_shop_name":"咕咕咕咕咕咕咕（）","work_shop_level":2,"wuhan_medal":false,"has_signed":false},"is_top":false,"n_likes":0,"is_liked":false,"content":"<p>emmmmmmmmmm………………</p>","n_comments":0,"updated_at":1503215729,"created_at":1503215729,"earliest_comments":[]},{"id":"36477","user":{"id":"224324","nickname":"小无无","avatar_url":"https://static.codemao.cn/FoXf4RvLE3xDl453bg6-4Cda8dh_","subject_id":0,"work_shop_name":"","work_shop_level":0,"wuhan_medal":false,"has_signed":false},"is_top":false,"n_likes":0,"is_liked":false,"content":"<p><img src=\"https://static.codemao.cn/Fh2MQpo8BuNTle6UcQ-hpgC0OJ9w\"><br></p>\n<p><br></p>","n_comments":0,"updated_at":1503208102,"created_at":1503208102,"earliest_comments":[]},{"id":"36345","user":{"id":"202350","nickname":"赵翊丞男一号.","avatar_url":"https://cdn-community.codemao.cn/47/community/1598269473583timg.jpg","subject_id":0,"work_shop_name":"","work_shop_level":0,"wuhan_medal":false,"has_signed":false},"is_top":false,"n_likes":0,"is_liked":false,"content":"<p><img src=\"https://static.codemao.cn/Fvxi9lRG-mQAjy2vZR5VJzJo1vRu\"><br></p>\n<p><br></p>","n_comments":3,"updated_at":1503121401,"created_at":1503121401,"earliest_comments":[{"id":"4442","user":{"id":"145690","nickname":"苏某","avatar_url":"https://static.codemao.cn/FqfZiNb9syfl1XOK5rA7h-n3J7XY","subject_id":928,"work_shop_name":"波特工作室","work_shop_level":1,"wuhan_medal":false,"has_signed":false},"n_likes":0,"is_liked":false,"content":"666","created_at":1530242361},{"id":"11431","user":{"id":"735691","nickname":"印泽恩Tim","avatar_url":"https://static.codemao.cn/codemaster/client/avatars/portrait_1.jpg","subject_id":859,"work_shop_name":"十字兄弟™有限公司","work_shop_level":2,"wuhan_medal":false,"has_signed":false},"n_likes":0,"is_liked":false,"reply_user":{"id":"145690","nickname":"苏某"},"content":"666","created_at":1533720196},{"id":"19380","user":{"id":"202350","nickname":"赵翊丞男一号.","avatar_url":"https://cdn-community.codemao.cn/47/community/1598269473583timg.jpg","subject_id":0,"work_shop_name":"","work_shop_level":0,"wuhan_medal":false,"has_signed":false},"n_likes":0,"is_liked":false,"content":"谢谢","created_at":1537067862}]},{"id":"36339","user":{"id":"202350","nickname":"赵翊丞男一号.","avatar_url":"https://cdn-community.codemao.cn/47/community/1598269473583timg.jpg","subject_id":0,"work_shop_name":"","work_shop_level":0,"wuhan_medal":false,"has_signed":false},"is_top":false,"n_likes":0,"is_liked":false,"content":"<p>用美图做行吗</p>","n_comments":0,"updated_at":1503120621,"created_at":1503120621,"earliest_comments":[]},{"id":"36330","user":{"id":"111543","nickname":"good  night","avatar_url":"https://static.codemao.cn/FtXsUtnBPFMUPzxpDcHYMkzVEl2q","subject_id":0,"work_shop_name":"","work_shop_level":0,"wuhan_medal":false,"has_signed":false},"is_top":false,"n_likes":0,"is_liked":false,"content":"<p><img src=\"https://static.codemao.cn/FvjeyJ9Ma1wW48H0vqaraeSZWGQq\"><br></p>\n<p><br></p>","n_comments":0,"updated_at":1503116717,"created_at":1503116717,"earliest_comments":[]},{"id":"36304","user":{"id":"214296","nickname":"主播喵副本","avatar_url":"https://static.codemao.cn/FmnbCWV2OzmsQSOnJc8r6Tte5W25","subject_id":0,"work_shop_name":"","work_shop_level":0,"wuhan_medal":false,"has_signed":false},"is_top":false,"n_likes":0,"is_liked":false,"content":"<p>emmmm</p>","n_comments":0,"updated_at":1503101946,"created_at":1503101946,"earliest_comments":[]},{"id":"36302","user":{"id":"179233","nickname":"杰鸽","avatar_url":"https://static.codemao.cn/Fj9WL32g3J_9Om1sWroOWquXZ25U","subject_id":0,"work_shop_name":"","work_shop_level":0,"wuhan_medal":false,"has_signed":false},"is_top":false,"n_likes":0,"is_liked":false,"content":"<p><img src=\"https://static.codemao.cn/Fkh8Fj4SESMynAPLgWgyvYzHaTkm\"><br></p>\n<p><br></p>","n_comments":0,"updated_at":1503101802,"created_at":1503101802,"earliest_comments":[]},{"id":"36295","user":{"id":"101954","nickname":"胡咚咚","avatar_url":"https://static.codemao.cn/a015bcb7-f868-4895-a24c-2410e4d13147","subject_id":0,"work_shop_name":"","work_shop_level":0,"wuhan_medal":false,"has_signed":false},"is_top":false,"n_likes":0,"is_liked":false,"content":"<p><p>黑云压城城欲摧<br> 王丫回归被人黑<br> 官方演技好逼真<br> 真不知道说什么<br> 胡言乱语<br> 严重低龄<br> 剧情幼稚<br> 学园孤岛<br> 喵！<br> 不好意思打错了<br> </p></p>","n_comments":0,"updated_at":1503061663,"created_at":1503061663,"earliest_comments":[]},{"id":"36292","user":{"id":"194148","nickname":"MAlopos","avatar_url":"https://cdn-community.codemao.cn/47/community/d2ViXzEwMDFfMTk0MTQ4XzE5NDE0OF8xNjEzMzExNDQ1ODY5XzZlYmRkN2E0.jpeg","subject_id":615,"work_shop_name":"萌新院","work_shop_level":2,"wuhan_medal":false,"has_signed":false},"is_top":false,"n_likes":0,"is_liked":false,"content":"<p><img src=\"https://static.codemao.cn/FkDsBwVtUc0hcG4BO6YOYahj4f0V\"><br></p>\n<p><br></p>","n_comments":0,"updated_at":1503060663,"created_at":1503060663,"earliest_comments":[]},{"id":"36291","user":{"id":"179233","nickname":"杰鸽","avatar_url":"https://static.codemao.cn/Fj9WL32g3J_9Om1sWroOWquXZ25U","subject_id":0,"work_shop_name":"","work_shop_level":0,"wuhan_medal":false,"has_signed":false},"is_top":false,"n_likes":0,"is_liked":false,"content":"<p>官方也学会发段子了？丨<img src=\"http://img.t.sinajs.cn/t4/appstyle/expression/ext/normal/b6/doge_thumb.gif\"></p>\n<p><br></p>","n_comments":0,"updated_at":1503060607,"created_at":1503060607,"earliest_comments":[]},{"id":"36290","user":{"id":"327139","nickname":"批小将","avatar_url":"https://static.codemao.cn/FviuX3_jRke2XjiySPv-4KAsj6HM","subject_id":0,"work_shop_name":"","work_shop_level":0,"wuhan_medal":false,"has_signed":false},"is_top":false,"n_likes":0,"is_liked":false,"content":"<p>糖！</p>","n_comments":0,"updated_at":1503060518,"created_at":1503060518,"earliest_comments":[]},{"id":"36286","user":{"id":"194148","nickname":"MAlopos","avatar_url":"https://cdn-community.codemao.cn/47/community/d2ViXzEwMDFfMTk0MTQ4XzE5NDE0OF8xNjEzMzExNDQ1ODY5XzZlYmRkN2E0.jpeg","subject_id":615,"work_shop_name":"萌新院","work_shop_level":2,"wuhan_medal":false,"has_signed":false},"is_top":false,"n_likes":0,"is_liked":false,"content":"<p><img src=\"https://static.codemao.cn/FgB2Wn6X6FsJLuAWVqK8goPHehx9\"><br></p>\n<p>私人订制漫画</p>","n_comments":0,"updated_at":1503059089,"created_at":1503059089,"earliest_comments":[]},{"id":"36284","user":{"id":"329705","nickname":"霖雨暮风","avatar_url":"https://static.codemao.cn/FqhpQ1lv41WITk-5Lz8uen7OLwUR","subject_id":0,"work_shop_name":"","work_shop_level":0,"wuhan_medal":false,"has_signed":false},"is_top":false,"n_likes":0,"is_liked":false,"content":"<p><img src=\"https://gss0.baidu.com/9vo3dSag_xI4khGko9WTAnF6hhy/zhidao/pic/item/aa18972bd40735fa67d1258d9d510fb30f2408e4.jpg\"></p>\n<p>想起了原梗</p>\n<p><br></p>","n_comments":2,"updated_at":1503058347,"created_at":1503058347,"earliest_comments":[{"id":"4893","user":{"id":"314171","nickname":"假编程猫258","avatar_url":"https://cdn-community.codemao.cn/47/community/d2ViXzEwMDFfMzE0MTcxXzMxNDE3MV8xNjU4Mzg4OTczNzc3XzMzMDRiYTk5.png","subject_id":211,"work_shop_name":"跃动工作室","work_shop_level":3,"wuhan_medal":false,"has_signed":false},"n_likes":0,"is_liked":false,"content":"最慢的IE浏览器","created_at":1530589402},{"id":"4904","user":{"id":"145690","nickname":"苏某","avatar_url":"https://static.codemao.cn/FqfZiNb9syfl1XOK5rA7h-n3J7XY","subject_id":928,"work_shop_name":"波特工作室","work_shop_level":1,"wuhan_medal":false,"has_signed":false},"n_likes":0,"is_liked":false,"content":"是的","created_at":1530600061}]},{"id":"36268","user":{"id":"224097","nickname":"蒜瓣儿","avatar_url":"https://static.codemao.cn/FhtP2klgY9cscyIWwyDsUTFs1_Bs","subject_id":0,"work_shop_name":"","work_shop_level":0,"wuhan_medal":false,"has_signed":false},"is_top":false,"n_likes":0,"is_liked":false,"content":"<p>哈哈哈哈这个好像很好玩</p>","n_comments":0,"updated_at":1503055918,"created_at":1503055918,"earliest_comments":[]},{"id":"36266","user":{"id":"327139","nickname":"批小将","avatar_url":"https://static.codemao.cn/FviuX3_jRke2XjiySPv-4KAsj6HM","subject_id":0,"work_shop_name":"","work_shop_level":0,"wuhan_medal":false,"has_signed":false},"is_top":false,"n_likes":0,"is_liked":false,"content":"<p><img src=\"https://static.codemao.cn/Fshqp0Fijr2y5yWoExWgoK2OlWTh\"><br></p>\n<p><br></p>","n_comments":0,"updated_at":1503054804,"created_at":1503054804,"earliest_comments":[]},{"id":"36264","user":{"id":"214296","nickname":"主播喵副本","avatar_url":"https://static.codemao.cn/FmnbCWV2OzmsQSOnJc8r6Tte5W25","subject_id":0,"work_shop_name":"","work_shop_level":0,"wuhan_medal":false,"has_signed":false},"is_top":false,"n_likes":0,"is_liked":false,"content":"<p>怎么没人说话了</p>","n_comments":0,"updated_at":1503053330,"created_at":1503053330,"earliest_comments":[]},{"id":"36263","user":{"id":"214296","nickname":"主播喵副本","avatar_url":"https://static.codemao.cn/FmnbCWV2OzmsQSOnJc8r6Tte5W25","subject_id":0,"work_shop_name":"","work_shop_level":0,"wuhan_medal":false,"has_signed":false},"is_top":false,"n_likes":0,"is_liked":false,"content":"<p>我还原了</p>","n_comments":0,"updated_at":1503052746,"created_at":1503052746,"earliest_comments":[]},{"id":"36262","user":{"id":"214296","nickname":"主播喵副本","avatar_url":"https://static.codemao.cn/FmnbCWV2OzmsQSOnJc8r6Tte5W25","subject_id":0,"work_shop_name":"","work_shop_level":0,"wuhan_medal":false,"has_signed":false},"is_top":false,"n_likes":0,"is_liked":false,"content":"<p>这张才是第一张图的原图</p>","n_comments":0,"updated_at":1503052741,"created_at":1503052741,"earliest_comments":[]},{"id":"36261","user":{"id":"201201","nickname":"编程猫王丫丫","avatar_url":"https://static.codemao.cn/Fqpb0swSeL7XHMe4lhXzOiX1PHgZ","subject_id":0,"work_shop_name":"","work_shop_level":0,"wuhan_medal":false,"has_signed":false},"is_top":false,"n_likes":0,"is_liked":false,"content":"<p><img src=\"http://img.t.sinajs.cn/t4/appstyle/expression/ext/normal/af/cry.gif\">难道我不是人见人爱的吗<br></p>\n<p><br></p>","n_comments":0,"updated_at":1503052664,"created_at":1503052664,"earliest_comments":[]},{"id":"36260","user":{"id":"214296","nickname":"主播喵副本","avatar_url":"https://static.codemao.cn/FmnbCWV2OzmsQSOnJc8r6Tte5W25","subject_id":0,"work_shop_name":"","work_shop_level":0,"wuhan_medal":false,"has_signed":false},"is_top":false,"n_likes":0,"is_liked":false,"content":"<p>图被改了</p>","n_comments":0,"updated_at":1503052581,"created_at":1503052581,"earliest_comments":[]},{"id":"36259","user":{"id":"214296","nickname":"主播喵副本","avatar_url":"https://static.codemao.cn/FmnbCWV2OzmsQSOnJc8r6Tte5W25","subject_id":0,"work_shop_name":"","work_shop_level":0,"wuhan_medal":false,"has_signed":false},"is_top":false,"n_likes":0,"is_liked":false,"content":"<p><img src=\"https://static.codemao.cn/FkvGt8abEMszOm40ufCWbD3CLjuT\"><br></p>\n<p>不过我想说，这才是原图</p>","n_comments":1,"updated_at":1503052542,"created_at":1503052542,"earliest_comments":[{"id":"6820","user":{"id":"204542","nickname":"Furiosco","avatar_url":"https://static.codemao.cn/codemaster/client/avatars//portrait_8.jpg","subject_id":0,"work_shop_name":"","work_shop_level":0,"wuhan_medal":false,"has_signed":false},"n_likes":0,"is_liked":false,"content":"呵呵","created_at":1531966111}]},{"id":"36258","user":{"id":"214296","nickname":"主播喵副本","avatar_url":"https://static.codemao.cn/FmnbCWV2OzmsQSOnJc8r6Tte5W25","subject_id":0,"work_shop_name":"","work_shop_level":0,"wuhan_medal":false,"has_signed":false},"is_top":false,"n_likes":0,"is_liked":false,"content":"<p>嗯</p>","n_comments":0,"updated_at":1503052413,"created_at":1503052413,"earliest_comments":[]},{"id":"36257","user":{"id":"201201","nickname":"编程猫王丫丫","avatar_url":"https://static.codemao.cn/Fqpb0swSeL7XHMe4lhXzOiX1PHgZ","subject_id":0,"work_shop_name":"","work_shop_level":0,"wuhan_medal":false,"has_signed":false},"is_top":false,"n_likes":0,"is_liked":false,"content":"<p>@<a rel=\"nofollow\">主播喵副本</a>&nbsp;反正也是孤家寡人，多一锅不如少一锅</p>\n<p><br></p>","n_comments":0,"updated_at":1503052393,"created_at":1503052393,"earliest_comments":[]}],"offset":0,"limit":30,"total":37,"counted":true}