{"items":[{"id":"1418946","user":{"id":"1493218968","nickname":"比那名居琪露诺_","avatar_url":"https://creation.bcmcdn.com//490/YW5kXzEwMDFfMTQ5MzIxODk2OF8wXzE3MzE4Mjk4Nzc1MzZfdEV4Vzhwamw=.jpg","subject_id":14351,"work_shop_name":"⑨","work_shop_level":2,"wuhan_medal":false,"has_signed":false},"is_top":false,"n_likes":0,"is_liked":false,"content":"<p>挖（（）</p>","n_comments":0,"updated_at":1669467727,"created_at":1669467727,"earliest_comments":[]},{"id":"1327577","user":{"id":"805064157","nickname":"LC_COOLCITY___QwQ","avatar_url":"https://cdn-community.codemao.cn/47/community/d2ViXzEwMDFfODA1MDY0MTU3XzgwNTA2NDE1N18xNjY5NzE4MzY2MTA3X2NlYzMwZmNl.png","subject_id":15042,"work_shop_name":"NCS","work_shop_level":0,"wuhan_medal":false,"has_signed":false},"is_top":false,"n_likes":0,"is_liked":false,"content":"<p><p>水水水水水水水水水水水水水水水水水水水水水水水水水水水水水水水水</p> \n<p>水水水水水水水水水水水水水水水水水水水水水水水水水水水水水水水水</p> \n<p>水水水水水水水水水水水水水水水水水水水水水水水水水水水水水水水水</p> \n<p>水水水水水水水水水水水水水水水水水水水水水水水水水水水水水水水水</p> \n<p>水水水水水水水水水水水水水水水水水水水水水水水水水水水水水水水水</p> \n<p>海</p></p>","n_comments":0,"updated_at":1659065277,"created_at":1659065277,"earliest_comments":[]},{"id":"52565","user":{"id":"139365","nickname":"韵律源点Arcaea","avatar_url":"https://cdn-community.codemao.cn/47/community/d2ViXzEwMDFfMTM5MzY1XzEzOTM2NV8xNjU0MDAxNjQ0NTE5XzI3MGQwOTRh.png","subject_id":5482,"work_shop_name":"咕咕咕咕咕咕咕（）","work_shop_level":2,"wuhan_medal":false,"has_signed":false},"is_top":false,"n_likes":0,"is_liked":false,"content":"<p>【水帖】粤230331号鉴定</p>","n_comments":0,"updated_at":1510650438,"created_at":1510650438,"earliest_comments":[]},{"id":"52564","user":{"id":"356532","nickname":"小丘mini","avatar_url":"https://static.codemao.cn/Ft5uwu_sJkUfPY6LlRuELTDwjj3c","subject_id":0,"work_shop_name":"","work_shop_level":0,"wuhan_medal":false,"has_signed":false},"is_top":false,"n_likes":0,"is_liked":false,"content":"<p>额，果然水贴</p>","n_comments":0,"updated_at":1510650193,"created_at":1510650193,"earliest_comments":[]},{"id":"52543","user":{"id":"375556","nickname":"假·冒险","avatar_url":"https://static.codemao.cn/FmCmDH3PgSakZT7KVF-DfJdQgFdu","subject_id":0,"work_shop_name":"","work_shop_level":0,"wuhan_medal":false,"has_signed":false},"is_top":false,"n_likes":0,"is_liked":false,"content":"<p>真是水的乳此清新脱俗</p>","n_comments":0,"updated_at":1510638874,"created_at":1510638874,"earliest_comments":[]}],"offset":0,"limit":30,"total":5,"counted":true}