{"id":"1847","user":{"id":"198522","nickname":"yhkun","avatar_url":"https://static.codemao.cn/Fj6rF5jLyas7LGfT2ntBjQfnddtw","subject_id":0,"work_shop_name":"","work_shop_level":0,"wuhan_medal":false,"has_signed":false},"title":"【彩蛋】黑客无敌手","content":"<p><p style=\"text-align:center;\"><iframe src=\"https://ide.codemao.cn/we/236389\" width=\"640\" height=\"498\"></iframe></p>\n<p><br></p></p>","board_id":"7","board_name":"灌水池塘","updated_at":1484904835,"created_at":1484904477,"n_views":97,"n_replies":4,"n_comments":0,"is_authorized":false,"is_featured":false,"is_hotted":false,"is_pinned":false,"tutorial_flag":0,"ask_help_flag":0}