{"id":"4397","user":{"id":"223645","nickname":"~断了个弦~","avatar_url":"https://static.codemao.cn/FnwvON0WCp3LGI6ji-sbZlAJt06r","subject_id":0,"work_shop_name":"","work_shop_level":0,"wuhan_medal":false,"has_signed":false},"title":"【魔性】就这样玩坏了","content":"<p><p style=\"text-align:center;\"><iframe src=\"https://ide.codemao.cn/we/756762\" width=\"640\" height=\"498\"></iframe></p>\n<p style=\"text-align:center;\">瞎了我的狗眼<img src=\"https://static.codemao.cn/FrJCXkSGO6LtjaW2IFwXozpHQ9HD\"><br></p>\n<p><br></p></p>","board_id":"7","board_name":"灌水池塘","updated_at":1497957129,"created_at":1497616296,"n_views":84,"n_replies":5,"n_comments":0,"is_authorized":false,"is_featured":false,"is_hotted":false,"is_pinned":false,"tutorial_flag":0,"ask_help_flag":0}