{"id":"1636","user":{"id":"133721","nickname":"四九圣尊","avatar_url":"https://static.codemao.cn/FpwY7hm51Irx8lFHBCthzIBrYbJt","subject_id":0,"work_shop_name":"","work_shop_level":0,"wuhan_medal":false,"has_signed":false},"title":"【征集】征集数据！","content":"<p><a rel=\"nofollow\"></a><a href=\"https://mobile.codemao.cn/player.html#206780\" rel=\"nofollow\">https://mobile.codemao.cn/player.html#206780</a></p>\n<p>来看看吧把这个机器下赢了以后把你下赢他的代码发给我，格式：</p>\n<p>（1是自己，2是机器）</p>\n<p>122</p>\n<p>112</p>\n<p>211（好了这盘我赢了）</p>\n<p>我要更新它的数据库，你们最终下不赢他的！！！！！！！！！！！</p>","board_id":"7","board_name":"灌水池塘","updated_at":1483850113,"created_at":1483620389,"n_views":165,"n_replies":6,"n_comments":0,"is_authorized":false,"is_featured":false,"is_hotted":false,"is_pinned":false,"tutorial_flag":0,"ask_help_flag":0}