{"id":"6039","user":{"id":"198522","nickname":"yhkun","avatar_url":"https://static.codemao.cn/Fj6rF5jLyas7LGfT2ntBjQfnddtw","subject_id":0,"work_shop_name":"","work_shop_level":0,"wuhan_medal":false,"has_signed":false},"title":"【学历】你的编程猫学历是？","content":"<p><p>初入萌新 </p>\n<p>进阶萌新 </p>\n<p>高级萌新 <font color=\"#00ffff\">&nbsp;me</font></p>\n<p>低级大佬 </p>\n<p>中级大佬 </p>\n<p>高级大佬 </p>\n<p>特级大佬 </p>\n<p>管理人员</p>\n<p><br></p></p>","board_id":"7","board_name":"灌水池塘","updated_at":1504006990,"created_at":1503989855,"n_views":128,"n_replies":23,"n_comments":0,"is_authorized":false,"is_featured":false,"is_hotted":false,"is_pinned":false,"tutorial_flag":0,"ask_help_flag":0}