{"id":"3871","user":{"id":"198522","nickname":"yhkun","avatar_url":"https://static.codemao.cn/Fj6rF5jLyas7LGfT2ntBjQfnddtw","subject_id":0,"work_shop_name":"","work_shop_level":0,"wuhan_medal":false,"has_signed":false},"title":"【讨论】为什么知乎上对易语言的态度总是不屑一顾？","content":"<p>摘自知乎</p>\n<p>易语言本来就没有任何创新。&nbsp;你自己在Visual&nbsp;C++里面#define几个中文token也能写出来一个所谓</p>\n<p><br></p>","board_id":"5","board_name":"你问我答","updated_at":1510466354,"created_at":1494650364,"n_views":149,"n_replies":3,"n_comments":2,"is_authorized":false,"is_featured":false,"is_hotted":false,"is_pinned":false,"tutorial_flag":0,"ask_help_flag":0}