{"id":"2613","user":{"id":"191084","nickname":"鹿晗 鹿乘风来","avatar_url":"https://cdn-community.codemao.cn/47/community/d2ViXzEwMDFfMTkxMDg0XzE5MTA4NF8xNjEwOTcwMzg2ODQ2XzkxZTc0Mjc3.jpeg","subject_id":0,"work_shop_name":"","work_shop_level":0,"wuhan_medal":false,"has_signed":false},"title":"【画面】怎么做小时画面？？","content":"<p>我不会做小说封面，会做的在下面留联，留下QQ号，帮我做一下</p>","board_id":"5","board_name":"你问我答","updated_at":1513918554,"created_at":1487426038,"n_views":116,"n_replies":16,"n_comments":0,"is_authorized":false,"is_featured":false,"is_hotted":false,"is_pinned":false,"tutorial_flag":0,"ask_help_flag":0}