{"id":"9247","user":{"id":"179794","nickname":"ftxqgfudi","avatar_url":"https://cdn-community.codemao.cn/community_frontend/community_default_avatar/avatar_300x300_01.jpg","subject_id":0,"work_shop_name":"","work_shop_level":0,"wuhan_medal":false,"has_signed":false},"title":"【推销】切水果","content":"<p>推销一下我的作品，切水果。</p>\n<p>上我的主页可见。</p>\n<p>当最终得分显示完毕之后会把你的得分计入排名哦~</p>","board_id":"17","board_name":"热门活动","updated_at":1518322538,"created_at":1518007887,"n_views":226,"n_replies":33,"n_comments":0,"is_authorized":false,"is_featured":false,"is_hotted":false,"is_pinned":false,"tutorial_flag":0,"ask_help_flag":0}